{
  "etat_modele": {
    "version": "ULTIME-1.0-iter5109",
    "score": 0.41471603529850654,
    "concepts": 161,
    "timestamp": "2025-09-27 15:47:15",
    "hash_modele": "e7b4bc971036"
  },
  "contexte_sauvegarde": {
    "raison": "variation_testee",
    "iteration": 5109,
    "statut_optimisation": "stagnation",
    "date_sauvegarde": "2025-09-27 15:47:15"
  },
  "metadata_originale": {
    "version": "ULTIME-1.0-iter5109",
    "date_creation": "2025-09-27 15:47:15",
    "concepts_totaux": 161,
    "source_variation": "optimisation_formules",
    "concepts_ajoutes": 6,
    "iteration_hill_climbing": 5109,
    "modele_parent": "ULTIME-1.0"
  }
}