{
  "etat_modele": {
    "version": "ULTIME-1.0-iter17467",
    "score": 0.41263268809259934,
    "concepts": 158,
    "timestamp": "2025-09-28 03:46:28",
    "hash_modele": "5bd939d38885"
  },
  "contexte_sauvegarde": {
    "raison": "variation_testee",
    "iteration": 17467,
    "statut_optimisation": "stagnation",
    "date_sauvegarde": "2025-09-28 03:46:28"
  },
  "metadata_originale": {
    "version": "ULTIME-1.0-iter17467",
    "date_creation": "2025-09-28 03:46:28",
    "concepts_totaux": 158,
    "source_variation": "variation_generique",
    "concepts_ajoutes": 4,
    "iteration_hill_climbing": 17467,
    "modele_parent": "ULTIME-1.0"
  }
}