{
  "etat_modele": {
    "version": "ULTIME-1.0-iter20825",
    "score": 0.44105557856928523,
    "concepts": 160,
    "timestamp": "2025-09-28 07:10:16",
    "hash_modele": "110069d4ab57"
  },
  "contexte_sauvegarde": {
    "raison": "variation_testee",
    "iteration": 20825,
    "statut_optimisation": "stagnation",
    "date_sauvegarde": "2025-09-28 07:10:16"
  },
  "metadata_originale": {
    "version": "ULTIME-1.0-iter20825",
    "date_creation": "2025-09-28 07:10:16",
    "concepts_totaux": 160,
    "source_variation": "concepts_emergents_avances",
    "concepts_ajoutes": 5,
    "iteration_hill_climbing": 20825,
    "modele_parent": "ULTIME-1.0"
  }
}