{
  "etat_modele": {
    "version": "ULTIME-1.0-iter22075",
    "score": 0.41690366433765613,
    "concepts": 161,
    "timestamp": "2025-09-28 08:27:03",
    "hash_modele": "6e61e16d5a8b"
  },
  "contexte_sauvegarde": {
    "raison": "variation_testee",
    "iteration": 22075,
    "statut_optimisation": "stagnation",
    "date_sauvegarde": "2025-09-28 08:27:03"
  },
  "metadata_originale": {
    "version": "ULTIME-1.0-iter22075",
    "date_creation": "2025-09-28 08:27:03",
    "concepts_totaux": 161,
    "source_variation": "optimisation_formules",
    "concepts_ajoutes": 6,
    "iteration_hill_climbing": 22075,
    "modele_parent": "ULTIME-1.0"
  }
}