{
  "etat_modele": {
    "version": "ULTIME-1.0-iter6058",
    "score": 0.41645338743801497,
    "concepts": 161,
    "timestamp": "2025-09-27 16:41:48",
    "hash_modele": "44ce4f730d51"
  },
  "contexte_sauvegarde": {
    "raison": "variation_testee",
    "iteration": 6058,
    "statut_optimisation": "stagnation",
    "date_sauvegarde": "2025-09-27 16:41:48"
  },
  "metadata_originale": {
    "version": "ULTIME-1.0-iter6058",
    "date_creation": "2025-09-27 16:41:48",
    "concepts_totaux": 161,
    "source_variation": "optimisation_formules",
    "concepts_ajoutes": 6,
    "iteration_hill_climbing": 6058,
    "modele_parent": "ULTIME-1.0"
  }
}