{
  "etat_modele": {
    "version": "ULTIME-1.0-iter9415",
    "score": 0.4282033699416007,
    "concepts": 158,
    "timestamp": "2025-09-27 19:53:13",
    "hash_modele": "43d6fed27dc1"
  },
  "contexte_sauvegarde": {
    "raison": "variation_testee",
    "iteration": 9415,
    "statut_optimisation": "stagnation",
    "date_sauvegarde": "2025-09-27 19:53:13"
  },
  "metadata_originale": {
    "version": "ULTIME-1.0-iter9415",
    "date_creation": "2025-09-27 19:53:13",
    "concepts_totaux": 158,
    "source_variation": "concepts_emergents_avances",
    "concepts_ajoutes": 3,
    "iteration_hill_climbing": 9415,
    "modele_parent": "ULTIME-1.0"
  }
}