{
  "etat_modele": {
    "version": "ULTIME-1.0-iter12145",
    "score": 0.4132945144103083,
    "concepts": 159,
    "timestamp": "2025-09-27 22:31:20",
    "hash_modele": "cc21243beb4c"
  },
  "contexte_sauvegarde": {
    "raison": "variation_testee",
    "iteration": 12145,
    "statut_optimisation": "stagnation",
    "date_sauvegarde": "2025-09-27 22:31:20"
  },
  "metadata_originale": {
    "version": "ULTIME-1.0-iter12145",
    "date_creation": "2025-09-27 22:31:20",
    "concepts_totaux": 159,
    "source_variation": "variation_generique",
    "concepts_ajoutes": 4,
    "iteration_hill_climbing": 12145,
    "modele_parent": "ULTIME-1.0"
  }
}