{
  "etat_modele": {
    "version": "ULTIME-1.0-iter19763",
    "score": 0.4259196691729443,
    "concepts": 169,
    "timestamp": "2025-09-28 06:05:31",
    "hash_modele": "8d0ab535688c"
  },
  "contexte_sauvegarde": {
    "raison": "variation_testee",
    "iteration": 19763,
    "statut_optimisation": "stagnation",
    "date_sauvegarde": "2025-09-28 06:05:31"
  },
  "metadata_originale": {
    "version": "ULTIME-1.0-iter19763",
    "date_creation": "2025-09-28 06:05:31",
    "concepts_totaux": 169,
    "source_variation": "expansion_aleatoire",
    "concepts_ajoutes": 14,
    "iteration_hill_climbing": 19763,
    "modele_parent": "ULTIME-1.0"
  }
}