{
  "etat_modele": {
    "version": "ULTIME-1.0-iter11145",
    "score": 0.45323385761977847,
    "concepts": 162,
    "timestamp": "2025-09-27 21:33:13",
    "hash_modele": "619a7a898a34"
  },
  "contexte_sauvegarde": {
    "raison": "variation_testee",
    "iteration": 11145,
    "statut_optimisation": "stagnation",
    "date_sauvegarde": "2025-09-27 21:33:13"
  },
  "metadata_originale": {
    "version": "ULTIME-1.0-iter11145",
    "date_creation": "2025-09-27 21:33:13",
    "concepts_totaux": 162,
    "source_variation": "concepts_emergents_avances",
    "concepts_ajoutes": 7,
    "iteration_hill_climbing": 11145,
    "modele_parent": "ULTIME-1.0"
  }
}