{
  "etat_modele": {
    "version": "ULTIME-1.0-iter22323",
    "score": 0.4132549341086885,
    "concepts": 159,
    "timestamp": "2025-09-28 08:42:22",
    "hash_modele": "158dc56c9e1a"
  },
  "contexte_sauvegarde": {
    "raison": "variation_testee",
    "iteration": 22323,
    "statut_optimisation": "stagnation",
    "date_sauvegarde": "2025-09-28 08:42:22"
  },
  "metadata_originale": {
    "version": "ULTIME-1.0-iter22323",
    "date_creation": "2025-09-28 08:42:22",
    "concepts_totaux": 159,
    "source_variation": "variation_generique",
    "concepts_ajoutes": 4,
    "iteration_hill_climbing": 22323,
    "modele_parent": "ULTIME-1.0"
  }
}