{
  "etat_modele": {
    "version": "ULTIME-1.0-iter18229",
    "score": 0.41772146215757566,
    "concepts": 162,
    "timestamp": "2025-09-28 04:32:22",
    "hash_modele": "e9a16984a48a"
  },
  "contexte_sauvegarde": {
    "raison": "variation_testee",
    "iteration": 18229,
    "statut_optimisation": "stagnation",
    "date_sauvegarde": "2025-09-28 04:32:22"
  },
  "metadata_originale": {
    "version": "ULTIME-1.0-iter18229",
    "date_creation": "2025-09-28 04:32:22",
    "concepts_totaux": 162,
    "source_variation": "optimisation_formules",
    "concepts_ajoutes": 7,
    "iteration_hill_climbing": 18229,
    "modele_parent": "ULTIME-1.0"
  }
}