{
  "etat_modele": {
    "version": "ULTIME-1.0-iter14534",
    "score": 0.419301199103986,
    "concepts": 165,
    "timestamp": "2025-09-28 00:51:36",
    "hash_modele": "26f6e657d302"
  },
  "contexte_sauvegarde": {
    "raison": "variation_testee",
    "iteration": 14534,
    "statut_optimisation": "stagnation",
    "date_sauvegarde": "2025-09-28 00:51:36"
  },
  "metadata_originale": {
    "version": "ULTIME-1.0-iter14534",
    "date_creation": "2025-09-28 00:51:36",
    "concepts_totaux": 165,
    "source_variation": "expansion_aleatoire",
    "concepts_ajoutes": 10,
    "iteration_hill_climbing": 14534,
    "modele_parent": "ULTIME-1.0"
  }
}