{
  "etat_modele": {
    "version": "ULTIME-1.0-iter9703",
    "score": 0.41721605308635434,
    "concepts": 162,
    "timestamp": "2025-09-27 20:09:47",
    "hash_modele": "96efed5214ca"
  },
  "contexte_sauvegarde": {
    "raison": "variation_testee",
    "iteration": 9703,
    "statut_optimisation": "stagnation",
    "date_sauvegarde": "2025-09-27 20:09:47"
  },
  "metadata_originale": {
    "version": "ULTIME-1.0-iter9703",
    "date_creation": "2025-09-27 20:09:47",
    "concepts_totaux": 162,
    "source_variation": "optimisation_formules",
    "concepts_ajoutes": 7,
    "iteration_hill_climbing": 9703,
    "modele_parent": "ULTIME-1.0"
  }
}