{
  "etat_modele": {
    "version": "ULTIME-1.0-iter10595",
    "score": 0.41864167342452097,
    "concepts": 163,
    "timestamp": "2025-09-27 21:01:14",
    "hash_modele": "14c9939f2e8f"
  },
  "contexte_sauvegarde": {
    "raison": "variation_testee",
    "iteration": 10595,
    "statut_optimisation": "stagnation",
    "date_sauvegarde": "2025-09-27 21:01:14"
  },
  "metadata_originale": {
    "version": "ULTIME-1.0-iter10595",
    "date_creation": "2025-09-27 21:01:14",
    "concepts_totaux": 163,
    "source_variation": "optimisation_formules",
    "concepts_ajoutes": 8,
    "iteration_hill_climbing": 10595,
    "modele_parent": "ULTIME-1.0"
  }
}