{
  "etat_modele": {
    "version": "ULTIME-1.0-iter6325",
    "score": 0.42853234417255126,
    "concepts": 158,
    "timestamp": "2025-09-27 16:56:56",
    "hash_modele": "d4ef8cbbde7c"
  },
  "contexte_sauvegarde": {
    "raison": "variation_testee",
    "iteration": 6325,
    "statut_optimisation": "stagnation",
    "date_sauvegarde": "2025-09-27 16:56:56"
  },
  "metadata_originale": {
    "version": "ULTIME-1.0-iter6325",
    "date_creation": "2025-09-27 16:56:56",
    "concepts_totaux": 158,
    "source_variation": "concepts_emergents_avances",
    "concepts_ajoutes": 3,
    "iteration_hill_climbing": 6325,
    "modele_parent": "ULTIME-1.0"
  }
}