{
  "etat_modele": {
    "version": "ULTIME-1.0-iter11807",
    "score": 0.41308512722961777,
    "concepts": 159,
    "timestamp": "2025-09-27 22:11:38",
    "hash_modele": "5e1a20d8c78c"
  },
  "contexte_sauvegarde": {
    "raison": "variation_testee",
    "iteration": 11807,
    "statut_optimisation": "stagnation",
    "date_sauvegarde": "2025-09-27 22:11:38"
  },
  "metadata_originale": {
    "version": "ULTIME-1.0-iter11807",
    "date_creation": "2025-09-27 22:11:38",
    "concepts_totaux": 159,
    "source_variation": "variation_generique",
    "concepts_ajoutes": 4,
    "iteration_hill_climbing": 11807,
    "modele_parent": "ULTIME-1.0"
  }
}