{
  "etat_modele": {
    "version": "ULTIME-1.0-iter764",
    "score": 0.44713649200145555,
    "concepts": 161,
    "timestamp": "2025-09-27 11:40:53",
    "hash_modele": "b65449a6b08b"
  },
  "contexte_sauvegarde": {
    "raison": "variation_testee",
    "iteration": 764,
    "statut_optimisation": "stagnation",
    "date_sauvegarde": "2025-09-27 11:40:53"
  },
  "metadata_originale": {
    "version": "ULTIME-1.0-iter764",
    "date_creation": "2025-09-27 11:40:53",
    "concepts_totaux": 161,
    "source_variation": "concepts_emergents_avances",
    "concepts_ajoutes": 6,
    "iteration_hill_climbing": 764,
    "modele_parent": "ULTIME-1.0"
  }
}