{
  "etat_modele": {
    "version": "ULTIME-1.0-iter22298",
    "score": 0.4167420925411064,
    "concepts": 162,
    "timestamp": "2025-09-28 08:40:50",
    "hash_modele": "c0e1e295a9c1"
  },
  "contexte_sauvegarde": {
    "raison": "variation_testee",
    "iteration": 22298,
    "statut_optimisation": "stagnation",
    "date_sauvegarde": "2025-09-28 08:40:50"
  },
  "metadata_originale": {
    "version": "ULTIME-1.0-iter22298",
    "date_creation": "2025-09-28 08:40:50",
    "concepts_totaux": 162,
    "source_variation": "expansion_aleatoire",
    "concepts_ajoutes": 7,
    "iteration_hill_climbing": 22298,
    "modele_parent": "ULTIME-1.0"
  }
}