{
  "etat_modele": {
    "version": "ULTIME-1.0-iter6813",
    "score": 0.42509905703072026,
    "concepts": 169,
    "timestamp": "2025-09-27 17:24:36",
    "hash_modele": "9edbeb0d6e8f"
  },
  "contexte_sauvegarde": {
    "raison": "variation_testee",
    "iteration": 6813,
    "statut_optimisation": "stagnation",
    "date_sauvegarde": "2025-09-27 17:24:37"
  },
  "metadata_originale": {
    "version": "ULTIME-1.0-iter6813",
    "date_creation": "2025-09-27 17:24:36",
    "concepts_totaux": 169,
    "source_variation": "expansion_aleatoire",
    "concepts_ajoutes": 14,
    "iteration_hill_climbing": 6813,
    "modele_parent": "ULTIME-1.0"
  }
}