{
  "etat_modele": {
    "version": "ULTIME-1.0-iter6177",
    "score": 0.41779399814973117,
    "concepts": 162,
    "timestamp": "2025-09-27 16:48:32",
    "hash_modele": "f613dbbef5cd"
  },
  "contexte_sauvegarde": {
    "raison": "variation_testee",
    "iteration": 6177,
    "statut_optimisation": "stagnation",
    "date_sauvegarde": "2025-09-27 16:48:32"
  },
  "metadata_originale": {
    "version": "ULTIME-1.0-iter6177",
    "date_creation": "2025-09-27 16:48:32",
    "concepts_totaux": 162,
    "source_variation": "optimisation_formules",
    "concepts_ajoutes": 7,
    "iteration_hill_climbing": 6177,
    "modele_parent": "ULTIME-1.0"
  }
}