{
  "etat_modele": {
    "version": "ULTIME-1.0-iter279",
    "score": 0.41333368868969855,
    "concepts": 159,
    "timestamp": "2025-09-27 11:12:52",
    "hash_modele": "01501fb4bdfe"
  },
  "contexte_sauvegarde": {
    "raison": "variation_testee",
    "iteration": 279,
    "statut_optimisation": "stagnation",
    "date_sauvegarde": "2025-09-27 11:12:52"
  },
  "metadata_originale": {
    "version": "ULTIME-1.0-iter279",
    "date_creation": "2025-09-27 11:12:52",
    "concepts_totaux": 159,
    "source_variation": "variation_generique",
    "concepts_ajoutes": 4,
    "iteration_hill_climbing": 279,
    "modele_parent": "ULTIME-1.0"
  }
}