{
  "etat_modele": {
    "version": "ULTIME-1.0-iter4761",
    "score": 0.4113487780185632,
    "concepts": 158,
    "timestamp": "2025-09-27 15:27:13",
    "hash_modele": "369877585a61"
  },
  "contexte_sauvegarde": {
    "raison": "variation_testee",
    "iteration": 4761,
    "statut_optimisation": "stagnation",
    "date_sauvegarde": "2025-09-27 15:27:13"
  },
  "metadata_originale": {
    "version": "ULTIME-1.0-iter4761",
    "date_creation": "2025-09-27 15:27:13",
    "concepts_totaux": 158,
    "source_variation": "optimisation_formules",
    "concepts_ajoutes": 3,
    "iteration_hill_climbing": 4761,
    "modele_parent": "ULTIME-1.0"
  }
}