{
  "etat_modele": {
    "version": "ULTIME-1.0-iter15765",
    "score": 0.41372124027928636,
    "concepts": 158,
    "timestamp": "2025-09-28 02:04:33",
    "hash_modele": "7be147bcf07e"
  },
  "contexte_sauvegarde": {
    "raison": "variation_testee",
    "iteration": 15765,
    "statut_optimisation": "stagnation",
    "date_sauvegarde": "2025-09-28 02:04:33"
  },
  "metadata_originale": {
    "version": "ULTIME-1.0-iter15765",
    "date_creation": "2025-09-28 02:04:33",
    "concepts_totaux": 158,
    "source_variation": "optimisation_formules",
    "concepts_ajoutes": 3,
    "iteration_hill_climbing": 15765,
    "modele_parent": "ULTIME-1.0"
  }
}