{
  "etat_modele": {
    "version": "ULTIME-1.0-iter9421",
    "score": 0.4209512700844067,
    "concepts": 162,
    "timestamp": "2025-09-27 19:53:37",
    "hash_modele": "7137806dc796"
  },
  "contexte_sauvegarde": {
    "raison": "variation_testee",
    "iteration": 9421,
    "statut_optimisation": "stagnation",
    "date_sauvegarde": "2025-09-27 19:53:37"
  },
  "metadata_originale": {
    "version": "ULTIME-1.0-iter9421",
    "date_creation": "2025-09-27 19:53:37",
    "concepts_totaux": 162,
    "source_variation": "optimisation_formules",
    "concepts_ajoutes": 7,
    "iteration_hill_climbing": 9421,
    "modele_parent": "ULTIME-1.0"
  }
}