{
  "etat_modele": {
    "version": "ULTIME-1.0-iter7775",
    "score": 0.4182756498247804,
    "concepts": 164,
    "timestamp": "2025-09-27 18:19:18",
    "hash_modele": "35ca6d9d038f"
  },
  "contexte_sauvegarde": {
    "raison": "variation_testee",
    "iteration": 7775,
    "statut_optimisation": "stagnation",
    "date_sauvegarde": "2025-09-27 18:19:18"
  },
  "metadata_originale": {
    "version": "ULTIME-1.0-iter7775",
    "date_creation": "2025-09-27 18:19:18",
    "concepts_totaux": 164,
    "source_variation": "expansion_aleatoire",
    "concepts_ajoutes": 9,
    "iteration_hill_climbing": 7775,
    "modele_parent": "ULTIME-1.0"
  }
}