{
  "etat_modele": {
    "version": "ULTIME-1.0-iter22719",
    "score": 0.4161762613583755,
    "concepts": 160,
    "timestamp": "2025-09-28 09:06:52",
    "hash_modele": "5cdc1070df3a"
  },
  "contexte_sauvegarde": {
    "raison": "variation_testee",
    "iteration": 22719,
    "statut_optimisation": "stagnation",
    "date_sauvegarde": "2025-09-28 09:06:52"
  },
  "metadata_originale": {
    "version": "ULTIME-1.0-iter22719",
    "date_creation": "2025-09-28 09:06:52",
    "concepts_totaux": 160,
    "source_variation": "optimisation_formules",
    "concepts_ajoutes": 5,
    "iteration_hill_climbing": 22719,
    "modele_parent": "ULTIME-1.0"
  }
}