{
  "etat_modele": {
    "version": "ULTIME-1.0-iter9726",
    "score": 0.4165517813889178,
    "concepts": 161,
    "timestamp": "2025-09-27 20:11:08",
    "hash_modele": "86096a1050e2"
  },
  "contexte_sauvegarde": {
    "raison": "variation_testee",
    "iteration": 9726,
    "statut_optimisation": "stagnation",
    "date_sauvegarde": "2025-09-27 20:11:08"
  },
  "metadata_originale": {
    "version": "ULTIME-1.0-iter9726",
    "date_creation": "2025-09-27 20:11:08",
    "concepts_totaux": 161,
    "source_variation": "optimisation_formules",
    "concepts_ajoutes": 6,
    "iteration_hill_climbing": 9726,
    "modele_parent": "ULTIME-1.0"
  }
}