{
  "etat_modele": {
    "version": "ULTIME-1.0-iter6385",
    "score": 0.4187313849180304,
    "concepts": 163,
    "timestamp": "2025-09-27 17:00:21",
    "hash_modele": "55230d224011"
  },
  "contexte_sauvegarde": {
    "raison": "variation_testee",
    "iteration": 6385,
    "statut_optimisation": "stagnation",
    "date_sauvegarde": "2025-09-27 17:00:21"
  },
  "metadata_originale": {
    "version": "ULTIME-1.0-iter6385",
    "date_creation": "2025-09-27 17:00:21",
    "concepts_totaux": 163,
    "source_variation": "optimisation_formules",
    "concepts_ajoutes": 8,
    "iteration_hill_climbing": 6385,
    "modele_parent": "ULTIME-1.0"
  }
}