{
  "etat_modele": {
    "version": "ULTIME-1.0-iter11438",
    "score": 0.42710347046999786,
    "concepts": 170,
    "timestamp": "2025-09-27 21:50:12",
    "hash_modele": "2b4bf913c969"
  },
  "contexte_sauvegarde": {
    "raison": "variation_testee",
    "iteration": 11438,
    "statut_optimisation": "stagnation",
    "date_sauvegarde": "2025-09-27 21:50:12"
  },
  "metadata_originale": {
    "version": "ULTIME-1.0-iter11438",
    "date_creation": "2025-09-27 21:50:12",
    "concepts_totaux": 170,
    "source_variation": "expansion_aleatoire",
    "concepts_ajoutes": 15,
    "iteration_hill_climbing": 11438,
    "modele_parent": "ULTIME-1.0"
  }
}