{
  "etat_modele": {
    "version": "ULTIME-1.0-iter11197",
    "score": 0.46099563664508636,
    "concepts": 163,
    "timestamp": "2025-09-27 21:36:14",
    "hash_modele": "0e23f64f14fe"
  },
  "contexte_sauvegarde": {
    "raison": "variation_testee",
    "iteration": 11197,
    "statut_optimisation": "stagnation",
    "date_sauvegarde": "2025-09-27 21:36:14"
  },
  "metadata_originale": {
    "version": "ULTIME-1.0-iter11197",
    "date_creation": "2025-09-27 21:36:14",
    "concepts_totaux": 163,
    "source_variation": "concepts_emergents_avances",
    "concepts_ajoutes": 8,
    "iteration_hill_climbing": 11197,
    "modele_parent": "ULTIME-1.0"
  }
}