{
  "etat_modele": {
    "version": "ULTIME-1.0-iter19649",
    "score": 0.4118484599462192,
    "concepts": 158,
    "timestamp": "2025-09-28 05:58:39",
    "hash_modele": "78a2314ae3e8"
  },
  "contexte_sauvegarde": {
    "raison": "variation_testee",
    "iteration": 19649,
    "statut_optimisation": "stagnation",
    "date_sauvegarde": "2025-09-28 05:58:39"
  },
  "metadata_originale": {
    "version": "ULTIME-1.0-iter19649",
    "date_creation": "2025-09-28 05:58:39",
    "concepts_totaux": 158,
    "source_variation": "variation_generique",
    "concepts_ajoutes": 4,
    "iteration_hill_climbing": 19649,
    "modele_parent": "ULTIME-1.0"
  }
}