{
  "etat_modele": {
    "version": "ULTIME-1.0-iter7391",
    "score": 0.4133254267846508,
    "concepts": 159,
    "timestamp": "2025-09-27 17:57:28",
    "hash_modele": "5b272484ad76"
  },
  "contexte_sauvegarde": {
    "raison": "variation_testee",
    "iteration": 7391,
    "statut_optimisation": "stagnation",
    "date_sauvegarde": "2025-09-27 17:57:28"
  },
  "metadata_originale": {
    "version": "ULTIME-1.0-iter7391",
    "date_creation": "2025-09-27 17:57:28",
    "concepts_totaux": 159,
    "source_variation": "variation_generique",
    "concepts_ajoutes": 4,
    "iteration_hill_climbing": 7391,
    "modele_parent": "ULTIME-1.0"
  }
}