{
  "etat_modele": {
    "version": "ULTIME-1.0-iter8350",
    "score": 0.42746815529971527,
    "concepts": 170,
    "timestamp": "2025-09-27 18:52:08",
    "hash_modele": "8f4ce402b91f"
  },
  "contexte_sauvegarde": {
    "raison": "variation_testee",
    "iteration": 8350,
    "statut_optimisation": "stagnation",
    "date_sauvegarde": "2025-09-27 18:52:08"
  },
  "metadata_originale": {
    "version": "ULTIME-1.0-iter8350",
    "date_creation": "2025-09-27 18:52:08",
    "concepts_totaux": 170,
    "source_variation": "expansion_aleatoire",
    "concepts_ajoutes": 15,
    "iteration_hill_climbing": 8350,
    "modele_parent": "ULTIME-1.0"
  }
}