{
  "etat_modele": {
    "version": "ULTIME-1.0-iter11338",
    "score": 0.41293505238087524,
    "concepts": 158,
    "timestamp": "2025-09-27 21:44:23",
    "hash_modele": "8659d2452f86"
  },
  "contexte_sauvegarde": {
    "raison": "variation_testee",
    "iteration": 11338,
    "statut_optimisation": "stagnation",
    "date_sauvegarde": "2025-09-27 21:44:23"
  },
  "metadata_originale": {
    "version": "ULTIME-1.0-iter11338",
    "date_creation": "2025-09-27 21:44:23",
    "concepts_totaux": 158,
    "source_variation": "variation_generique",
    "concepts_ajoutes": 4,
    "iteration_hill_climbing": 11338,
    "modele_parent": "ULTIME-1.0"
  }
}