{
  "etat_modele": {
    "version": "ULTIME-1.0-iter19391",
    "score": 0.4274463821831862,
    "concepts": 158,
    "timestamp": "2025-09-28 05:42:57",
    "hash_modele": "d0f516716b24"
  },
  "contexte_sauvegarde": {
    "raison": "variation_testee",
    "iteration": 19391,
    "statut_optimisation": "stagnation",
    "date_sauvegarde": "2025-09-28 05:42:57"
  },
  "metadata_originale": {
    "version": "ULTIME-1.0-iter19391",
    "date_creation": "2025-09-28 05:42:57",
    "concepts_totaux": 158,
    "source_variation": "concepts_emergents_avances",
    "concepts_ajoutes": 3,
    "iteration_hill_climbing": 19391,
    "modele_parent": "ULTIME-1.0"
  }
}