{
  "etat_modele": {
    "version": "ULTIME-1.0-iter6754",
    "score": 0.413415019292394,
    "concepts": 159,
    "timestamp": "2025-09-27 17:21:14",
    "hash_modele": "8f46dec993e0"
  },
  "contexte_sauvegarde": {
    "raison": "variation_testee",
    "iteration": 6754,
    "statut_optimisation": "stagnation",
    "date_sauvegarde": "2025-09-27 17:21:14"
  },
  "metadata_originale": {
    "version": "ULTIME-1.0-iter6754",
    "date_creation": "2025-09-27 17:21:14",
    "concepts_totaux": 159,
    "source_variation": "variation_generique",
    "concepts_ajoutes": 4,
    "iteration_hill_climbing": 6754,
    "modele_parent": "ULTIME-1.0"
  }
}