{
  "etat_modele": {
    "version": "ULTIME-1.0-iter22146",
    "score": 0.4142966801495781,
    "concepts": 159,
    "timestamp": "2025-09-28 08:31:27",
    "hash_modele": "a05a70109390"
  },
  "contexte_sauvegarde": {
    "raison": "variation_testee",
    "iteration": 22146,
    "statut_optimisation": "stagnation",
    "date_sauvegarde": "2025-09-28 08:31:27"
  },
  "metadata_originale": {
    "version": "ULTIME-1.0-iter22146",
    "date_creation": "2025-09-28 08:31:27",
    "concepts_totaux": 159,
    "source_variation": "variation_generique",
    "concepts_ajoutes": 4,
    "iteration_hill_climbing": 22146,
    "modele_parent": "ULTIME-1.0"
  }
}