{
  "etat_modele": {
    "version": "ULTIME-1.0-iter11558",
    "score": 0.413724887565485,
    "concepts": 159,
    "timestamp": "2025-09-27 21:57:10",
    "hash_modele": "a609d561ab65"
  },
  "contexte_sauvegarde": {
    "raison": "variation_testee",
    "iteration": 11558,
    "statut_optimisation": "stagnation",
    "date_sauvegarde": "2025-09-27 21:57:10"
  },
  "metadata_originale": {
    "version": "ULTIME-1.0-iter11558",
    "date_creation": "2025-09-27 21:57:10",
    "concepts_totaux": 159,
    "source_variation": "variation_generique",
    "concepts_ajoutes": 4,
    "iteration_hill_climbing": 11558,
    "modele_parent": "ULTIME-1.0"
  }
}