{
  "etat_modele": {
    "version": "ULTIME-1.0-iter294",
    "score": 0.4146900417601268,
    "concepts": 160,
    "timestamp": "2025-09-27 10:23:41",
    "hash_modele": "c0c1a335bd77"
  },
  "contexte_sauvegarde": {
    "raison": "variation_testee",
    "iteration": 294,
    "statut_optimisation": "stagnation",
    "date_sauvegarde": "2025-09-27 10:23:41"
  },
  "metadata_originale": {
    "version": "ULTIME-1.0-iter294",
    "date_creation": "2025-09-27 10:23:41",
    "concepts_totaux": 160,
    "source_variation": "optimisation_formules",
    "concepts_ajoutes": 5,
    "iteration_hill_climbing": 294,
    "modele_parent": "ULTIME-1.0"
  }
}