{
  "etat_modele": {
    "version": "ULTIME-1.0-iter3153",
    "score": 0.4242149708341426,
    "concepts": 169,
    "timestamp": "2025-09-27 13:55:31",
    "hash_modele": "b55324e2e007"
  },
  "contexte_sauvegarde": {
    "raison": "variation_testee",
    "iteration": 3153,
    "statut_optimisation": "stagnation",
    "date_sauvegarde": "2025-09-27 13:55:31"
  },
  "metadata_originale": {
    "version": "ULTIME-1.0-iter3153",
    "date_creation": "2025-09-27 13:55:31",
    "concepts_totaux": 169,
    "source_variation": "expansion_aleatoire",
    "concepts_ajoutes": 14,
    "iteration_hill_climbing": 3153,
    "modele_parent": "ULTIME-1.0"
  }
}