{
  "etat_modele": {
    "version": "ULTIME-1.0-iter3022",
    "score": 0.4256064109396924,
    "concepts": 170,
    "timestamp": "2025-09-27 13:47:51",
    "hash_modele": "55d58803df6e"
  },
  "contexte_sauvegarde": {
    "raison": "variation_testee",
    "iteration": 3022,
    "statut_optimisation": "stagnation",
    "date_sauvegarde": "2025-09-27 13:47:51"
  },
  "metadata_originale": {
    "version": "ULTIME-1.0-iter3022",
    "date_creation": "2025-09-27 13:47:51",
    "concepts_totaux": 170,
    "source_variation": "expansion_aleatoire",
    "concepts_ajoutes": 15,
    "iteration_hill_climbing": 3022,
    "modele_parent": "ULTIME-1.0"
  }
}