{
  "etat_modele": {
    "version": "ULTIME-1.0-iter15373",
    "score": 0.4205959023163771,
    "concepts": 166,
    "timestamp": "2025-09-28 01:41:15",
    "hash_modele": "c96f69d726b6"
  },
  "contexte_sauvegarde": {
    "raison": "variation_testee",
    "iteration": 15373,
    "statut_optimisation": "stagnation",
    "date_sauvegarde": "2025-09-28 01:41:15"
  },
  "metadata_originale": {
    "version": "ULTIME-1.0-iter15373",
    "date_creation": "2025-09-28 01:41:15",
    "concepts_totaux": 166,
    "source_variation": "expansion_aleatoire",
    "concepts_ajoutes": 11,
    "iteration_hill_climbing": 15373,
    "modele_parent": "ULTIME-1.0"
  }
}