{
  "etat_modele": {
    "version": "ULTIME-1.0-iter17659",
    "score": 0.4129556314445506,
    "concepts": 159,
    "timestamp": "2025-09-28 03:58:01",
    "hash_modele": "4607268e1899"
  },
  "contexte_sauvegarde": {
    "raison": "variation_testee",
    "iteration": 17659,
    "statut_optimisation": "stagnation",
    "date_sauvegarde": "2025-09-28 03:58:01"
  },
  "metadata_originale": {
    "version": "ULTIME-1.0-iter17659",
    "date_creation": "2025-09-28 03:58:01",
    "concepts_totaux": 159,
    "source_variation": "variation_generique",
    "concepts_ajoutes": 4,
    "iteration_hill_climbing": 17659,
    "modele_parent": "ULTIME-1.0"
  }
}