{
  "etat_modele": {
    "version": "ULTIME-1.0-iter20897",
    "score": 0.44110574742038855,
    "concepts": 160,
    "timestamp": "2025-09-28 07:14:40",
    "hash_modele": "d800ec5bd939"
  },
  "contexte_sauvegarde": {
    "raison": "variation_testee",
    "iteration": 20897,
    "statut_optimisation": "stagnation",
    "date_sauvegarde": "2025-09-28 07:14:40"
  },
  "metadata_originale": {
    "version": "ULTIME-1.0-iter20897",
    "date_creation": "2025-09-28 07:14:40",
    "concepts_totaux": 160,
    "source_variation": "concepts_emergents_avances",
    "concepts_ajoutes": 5,
    "iteration_hill_climbing": 20897,
    "modele_parent": "ULTIME-1.0"
  }
}