{
  "etat_modele": {
    "version": "ULTIME-1.0-iter18829",
    "score": 0.46039060113430885,
    "concepts": 163,
    "timestamp": "2025-09-28 05:08:48",
    "hash_modele": "827d6f39fd03"
  },
  "contexte_sauvegarde": {
    "raison": "variation_testee",
    "iteration": 18829,
    "statut_optimisation": "stagnation",
    "date_sauvegarde": "2025-09-28 05:08:48"
  },
  "metadata_originale": {
    "version": "ULTIME-1.0-iter18829",
    "date_creation": "2025-09-28 05:08:48",
    "concepts_totaux": 163,
    "source_variation": "concepts_emergents_avances",
    "concepts_ajoutes": 8,
    "iteration_hill_climbing": 18829,
    "modele_parent": "ULTIME-1.0"
  }
}