{
  "etat_modele": {
    "version": "ULTIME-1.0-iter18805",
    "score": 0.4543253050793267,
    "concepts": 162,
    "timestamp": "2025-09-28 05:07:21",
    "hash_modele": "85ebb7a16fa5"
  },
  "contexte_sauvegarde": {
    "raison": "variation_testee",
    "iteration": 18805,
    "statut_optimisation": "stagnation",
    "date_sauvegarde": "2025-09-28 05:07:21"
  },
  "metadata_originale": {
    "version": "ULTIME-1.0-iter18805",
    "date_creation": "2025-09-28 05:07:21",
    "concepts_totaux": 162,
    "source_variation": "concepts_emergents_avances",
    "concepts_ajoutes": 7,
    "iteration_hill_climbing": 18805,
    "modele_parent": "ULTIME-1.0"
  }
}