{
  "etat_modele": {
    "version": "ULTIME-1.0-iter5373",
    "score": 0.41484572587032853,
    "concepts": 162,
    "timestamp": "2025-09-27 16:02:43",
    "hash_modele": "6c59a7a9afc7"
  },
  "contexte_sauvegarde": {
    "raison": "variation_testee",
    "iteration": 5373,
    "statut_optimisation": "stagnation",
    "date_sauvegarde": "2025-09-27 16:02:43"
  },
  "metadata_originale": {
    "version": "ULTIME-1.0-iter5373",
    "date_creation": "2025-09-27 16:02:43",
    "concepts_totaux": 162,
    "source_variation": "expansion_aleatoire",
    "concepts_ajoutes": 7,
    "iteration_hill_climbing": 5373,
    "modele_parent": "ULTIME-1.0"
  }
}