{
  "etat_modele": {
    "version": "ULTIME-1.0-iter17458",
    "score": 0.4144518366769221,
    "concepts": 160,
    "timestamp": "2025-09-28 03:45:57",
    "hash_modele": "b375694e2c28"
  },
  "contexte_sauvegarde": {
    "raison": "variation_testee",
    "iteration": 17458,
    "statut_optimisation": "stagnation",
    "date_sauvegarde": "2025-09-28 03:45:57"
  },
  "metadata_originale": {
    "version": "ULTIME-1.0-iter17458",
    "date_creation": "2025-09-28 03:45:57",
    "concepts_totaux": 160,
    "source_variation": "expansion_aleatoire",
    "concepts_ajoutes": 5,
    "iteration_hill_climbing": 17458,
    "modele_parent": "ULTIME-1.0"
  }
}