{
  "etat_modele": {
    "version": "ULTIME-1.0-iter380",
    "score": 0.4202686246502291,
    "concepts": 165,
    "timestamp": "2025-09-27 10:26:39",
    "hash_modele": "181e20224830"
  },
  "contexte_sauvegarde": {
    "raison": "variation_testee",
    "iteration": 380,
    "statut_optimisation": "stagnation",
    "date_sauvegarde": "2025-09-27 10:26:39"
  },
  "metadata_originale": {
    "version": "ULTIME-1.0-iter380",
    "date_creation": "2025-09-27 10:26:39",
    "concepts_totaux": 165,
    "source_variation": "expansion_aleatoire",
    "concepts_ajoutes": 10,
    "iteration_hill_climbing": 380,
    "modele_parent": "ULTIME-1.0"
  }
}