{
  "etat_modele": {
    "version": "ULTIME-1.0-iter23533",
    "score": 0.43478537618658664,
    "concepts": 159,
    "timestamp": "2025-09-28 09:57:48",
    "hash_modele": "4099b3e71e59"
  },
  "contexte_sauvegarde": {
    "raison": "variation_testee",
    "iteration": 23533,
    "statut_optimisation": "stagnation",
    "date_sauvegarde": "2025-09-28 09:57:48"
  },
  "metadata_originale": {
    "version": "ULTIME-1.0-iter23533",
    "date_creation": "2025-09-28 09:57:48",
    "concepts_totaux": 159,
    "source_variation": "concepts_emergents_avances",
    "concepts_ajoutes": 4,
    "iteration_hill_climbing": 23533,
    "modele_parent": "ULTIME-1.0"
  }
}