{
  "etat_modele": {
    "version": "ULTIME-1.0-iter13638",
    "score": 0.41210839168431157,
    "concepts": 158,
    "timestamp": "2025-09-27 23:58:44",
    "hash_modele": "9258e5e0f385"
  },
  "contexte_sauvegarde": {
    "raison": "variation_testee",
    "iteration": 13638,
    "statut_optimisation": "stagnation",
    "date_sauvegarde": "2025-09-27 23:58:44"
  },
  "metadata_originale": {
    "version": "ULTIME-1.0-iter13638",
    "date_creation": "2025-09-27 23:58:44",
    "concepts_totaux": 158,
    "source_variation": "variation_generique",
    "concepts_ajoutes": 4,
    "iteration_hill_climbing": 13638,
    "modele_parent": "ULTIME-1.0"
  }
}