{
  "etat_modele": {
    "version": "ULTIME-1.0-iter23394",
    "score": 0.4125794882136946,
    "concepts": 158,
    "timestamp": "2025-09-28 09:48:46",
    "hash_modele": "11f7b5402536"
  },
  "contexte_sauvegarde": {
    "raison": "variation_testee",
    "iteration": 23394,
    "statut_optimisation": "stagnation",
    "date_sauvegarde": "2025-09-28 09:48:46"
  },
  "metadata_originale": {
    "version": "ULTIME-1.0-iter23394",
    "date_creation": "2025-09-28 09:48:46",
    "concepts_totaux": 158,
    "source_variation": "variation_generique",
    "concepts_ajoutes": 4,
    "iteration_hill_climbing": 23394,
    "modele_parent": "ULTIME-1.0"
  }
}