{
  "etat_modele": {
    "version": "ULTIME-1.0-iter15618",
    "score": 0.423183948878313,
    "concepts": 168,
    "timestamp": "2025-09-28 01:55:47",
    "hash_modele": "900c45fb945b"
  },
  "contexte_sauvegarde": {
    "raison": "variation_testee",
    "iteration": 15618,
    "statut_optimisation": "stagnation",
    "date_sauvegarde": "2025-09-28 01:55:47"
  },
  "metadata_originale": {
    "version": "ULTIME-1.0-iter15618",
    "date_creation": "2025-09-28 01:55:47",
    "concepts_totaux": 168,
    "source_variation": "expansion_aleatoire",
    "concepts_ajoutes": 13,
    "iteration_hill_climbing": 15618,
    "modele_parent": "ULTIME-1.0"
  }
}