{
  "etat_modele": {
    "version": "ULTIME-1.0-iter16759",
    "score": 0.41405522165890596,
    "concepts": 159,
    "timestamp": "2025-09-28 03:03:55",
    "hash_modele": "0751c6a47cc5"
  },
  "contexte_sauvegarde": {
    "raison": "variation_testee",
    "iteration": 16759,
    "statut_optimisation": "stagnation",
    "date_sauvegarde": "2025-09-28 03:03:55"
  },
  "metadata_originale": {
    "version": "ULTIME-1.0-iter16759",
    "date_creation": "2025-09-28 03:03:55",
    "concepts_totaux": 159,
    "source_variation": "variation_generique",
    "concepts_ajoutes": 4,
    "iteration_hill_climbing": 16759,
    "modele_parent": "ULTIME-1.0"
  }
}