{
  "etat_modele": {
    "version": "ULTIME-1.0-iter7201",
    "score": 0.4132047793198672,
    "concepts": 158,
    "timestamp": "2025-09-27 17:46:44",
    "hash_modele": "c59bd8d5c62e"
  },
  "contexte_sauvegarde": {
    "raison": "variation_testee",
    "iteration": 7201,
    "statut_optimisation": "stagnation",
    "date_sauvegarde": "2025-09-27 17:46:44"
  },
  "metadata_originale": {
    "version": "ULTIME-1.0-iter7201",
    "date_creation": "2025-09-27 17:46:44",
    "concepts_totaux": 158,
    "source_variation": "variation_generique",
    "concepts_ajoutes": 4,
    "iteration_hill_climbing": 7201,
    "modele_parent": "ULTIME-1.0"
  }
}