{
  "etat_modele": {
    "version": "ULTIME-1.0-iter470",
    "score": 0.41525172806307975,
    "concepts": 161,
    "timestamp": "2025-09-27 10:29:46",
    "hash_modele": "fd4c2b115fed"
  },
  "contexte_sauvegarde": {
    "raison": "variation_testee",
    "iteration": 470,
    "statut_optimisation": "stagnation",
    "date_sauvegarde": "2025-09-27 10:29:46"
  },
  "metadata_originale": {
    "version": "ULTIME-1.0-iter470",
    "date_creation": "2025-09-27 10:29:46",
    "concepts_totaux": 161,
    "source_variation": "optimisation_formules",
    "concepts_ajoutes": 6,
    "iteration_hill_climbing": 470,
    "modele_parent": "ULTIME-1.0"
  }
}