{
  "etat_modele": {
    "version": "ULTIME-1.0-iter10651",
    "score": 0.41339747757471723,
    "concepts": 159,
    "timestamp": "2025-09-27 21:04:28",
    "hash_modele": "6c8f7eb57b4c"
  },
  "contexte_sauvegarde": {
    "raison": "variation_testee",
    "iteration": 10651,
    "statut_optimisation": "stagnation",
    "date_sauvegarde": "2025-09-27 21:04:28"
  },
  "metadata_originale": {
    "version": "ULTIME-1.0-iter10651",
    "date_creation": "2025-09-27 21:04:28",
    "concepts_totaux": 159,
    "source_variation": "variation_generique",
    "concepts_ajoutes": 4,
    "iteration_hill_climbing": 10651,
    "modele_parent": "ULTIME-1.0"
  }
}