{
  "etat_modele": {
    "version": "ULTIME-1.0-iter1604",
    "score": 0.422328928182224,
    "concepts": 166,
    "timestamp": "2025-09-27 12:28:12",
    "hash_modele": "8668972b24b3"
  },
  "contexte_sauvegarde": {
    "raison": "variation_testee",
    "iteration": 1604,
    "statut_optimisation": "stagnation",
    "date_sauvegarde": "2025-09-27 12:28:12"
  },
  "metadata_originale": {
    "version": "ULTIME-1.0-iter1604",
    "date_creation": "2025-09-27 12:28:12",
    "concepts_totaux": 166,
    "source_variation": "expansion_aleatoire",
    "concepts_ajoutes": 11,
    "iteration_hill_climbing": 1604,
    "modele_parent": "ULTIME-1.0"
  }
}