{
  "etat_modele": {
    "version": "ULTIME-1.0-iter428",
    "score": 0.4132353751722504,
    "concepts": 159,
    "timestamp": "2025-09-27 10:28:19",
    "hash_modele": "d09741e8d5bb"
  },
  "contexte_sauvegarde": {
    "raison": "variation_testee",
    "iteration": 428,
    "statut_optimisation": "stagnation",
    "date_sauvegarde": "2025-09-27 10:28:19"
  },
  "metadata_originale": {
    "version": "ULTIME-1.0-iter428",
    "date_creation": "2025-09-27 10:28:18",
    "concepts_totaux": 159,
    "source_variation": "variation_generique",
    "concepts_ajoutes": 4,
    "iteration_hill_climbing": 428,
    "modele_parent": "ULTIME-1.0"
  }
}