{
  "etat_modele": {
    "version": "ULTIME-1.0-iter8607",
    "score": 0.4239903885652512,
    "concepts": 167,
    "timestamp": "2025-09-27 19:06:51",
    "hash_modele": "b98a9447e163"
  },
  "contexte_sauvegarde": {
    "raison": "variation_testee",
    "iteration": 8607,
    "statut_optimisation": "stagnation",
    "date_sauvegarde": "2025-09-27 19:06:51"
  },
  "metadata_originale": {
    "version": "ULTIME-1.0-iter8607",
    "date_creation": "2025-09-27 19:06:51",
    "concepts_totaux": 167,
    "source_variation": "expansion_aleatoire",
    "concepts_ajoutes": 12,
    "iteration_hill_climbing": 8607,
    "modele_parent": "ULTIME-1.0"
  }
}